ropemode/__init__.py
ropemode/decorators.py
ropemode/dialog.py
ropemode/environment.py
ropemode/filter.py
ropemode/interface.py
ropemode/refactor.py
ropemode-0.6.1.dist-info/COPYING
ropemode-0.6.1.dist-info/METADATA
ropemode-0.6.1.dist-info/WHEEL
ropemode-0.6.1.dist-info/top_level.txt
ropemode-0.6.1.dist-info/RECORD
