Metadata-Version: 2.1
Name: ropemode
Version: 0.6.1
Summary: a helper for using rope refactoring library in IDEs
Author-email: Ali Gholami Rudi <aligrudi@users.sourceforge.net>
Maintainer-email: Lie Ryan <lieryan.24@proton.me>
License: GNU GPL
Project-URL: Source, https://github.com/python-rope/ropemode
Classifier: Development Status :: 4 - Beta
Classifier: Operating System :: OS Independent
Classifier: Environment :: X11 Applications
Classifier: Environment :: Win32 (MS Windows)
Classifier: Environment :: MacOS X
Classifier: Intended Audience :: Developers
Classifier: License :: OSI Approved :: GNU General Public License (GPL)
Classifier: Natural Language :: English
Classifier: Programming Language :: Python
Classifier: Topic :: Software Development
Requires-Dist: rope (>=0.9.4)
Provides-Extra: dev
Requires-Dist: build (>=0.7.0) ; extra == 'dev'
Requires-Dist: twine (>=4.0.0) ; extra == 'dev'
